Metadata-Version: 2.1
Name: gallas-dist
Version: 0.1
Summary: Gaussian distributions
Home-page: UNKNOWN
Author: Gallas
Author-email: fniang89@gmail.com
License: UNKNOWN
Platform: UNKNOWN
